stateset_embedded-0.1.7.dist-info/METADATA
stateset_embedded-0.1.7.dist-info/WHEEL
stateset_embedded/__init__.py
stateset_embedded/__init__.pyi
stateset_embedded/__pycache__/__init__.cpython-310.pyc
stateset_embedded/py.typed
stateset_embedded/stateset_embedded.cpython-38-x86_64-linux-gnu.so
stateset_embedded-0.1.7.dist-info/RECORD
